statefun/__init__.py
statefun/context.py
statefun/core.py
statefun/egress_io.py
statefun/kafka_egress_pb2.py
statefun/kinesis_egress_pb2.py
statefun/messages.py
statefun/request_reply_pb2.py
statefun/request_reply_v3.py
statefun/statefun_builder.py
statefun/storage.py
statefun/types_pb2.py
statefun/utils.py
statefun/wrapper_types.py
apache_flink_statefun-3.3.0.dist-info/LICENSE
apache_flink_statefun-3.3.0.dist-info/METADATA
apache_flink_statefun-3.3.0.dist-info/NOTICE
apache_flink_statefun-3.3.0.dist-info/WHEEL
apache_flink_statefun-3.3.0.dist-info/top_level.txt
apache_flink_statefun-3.3.0.dist-info/RECORD
